Metadata-Version: 2.1
Name: data-analyzer
Version: 0.0.1
Summary: Auto EDA package
Author: KSV Muralidhar
Author-email: murali_dhar0552@yahoo.com
License: MIT
Platform: UNKNOWN
Classifier: Programming Language :: Python :: 3
Classifier: License :: OSI Approved :: MIT License
Requires-Python: >=3.7
License-File: LICENSE
